AUTHORS
LICENSE
MANIFEST.in
README.md
setup.py
django_passwordless.egg-info/PKG-INFO
django_passwordless.egg-info/SOURCES.txt
django_passwordless.egg-info/dependency_links.txt
django_passwordless.egg-info/not-zip-safe
django_passwordless.egg-info/top_level.txt
passwordless/__init__.py
passwordless/admin.py
passwordless/apps.py
passwordless/defaults.py
passwordless/forms.py
passwordless/models.py
passwordless/tasks.py
passwordless/tests.py
passwordless/views.py
passwordless/management/__init__.py
passwordless/management/commands/__init__.py
passwordless/management/commands/clearpasswordless.py
passwordless/migrations/0001_initial.py
passwordless/migrations/__init__.py
passwordless/templates/passwordless/changeemail_otp.html
passwordless/templates/passwordless/changeemail_otp_unknown.html
passwordless/templates/passwordless/changeemail_request.html
passwordless/templates/passwordless/login_otp.html
passwordless/templates/passwordless/login_otp_ratelimit.html
passwordless/templates/passwordless/login_otp_unknown.html
passwordless/templates/passwordless/login_request.html
passwordless/templates/passwordless/email/changeemail_message.html
passwordless/templates/passwordless/email/changeemail_message.txt
passwordless/templates/passwordless/email/changeemail_subject.txt
passwordless/templates/passwordless/email/login_message.html
passwordless/templates/passwordless/email/login_message.txt
passwordless/templates/passwordless/email/login_subject.txt
passwordless/templates/passwordless/messages/changeemail_success.html
passwordless/templates/passwordless/messages/createuser_success.html
passwordless/templates/passwordless/messages/login_success.html